MANIFEST.in
README.md
setup.py
explain_commands/__init__.py
explain_commands/management/__init__.py
explain_commands/management/commands/__init__.py
explain_commands/management/commands/explain_commands.py