Metadata-Version: 1.0
Name: django-explain-commands
Version: 0.2
Summary: Django app for explaining where commands are coming from.
Home-page: https://github.com/jellycrystal/django-explain-commands
Author: Yury Yurevich
Author-email: yyurevich@jellycrystal.com
License: BSD
Platform: UNKNOWN
Classifier: Development Status :: 4 - Beta
Classifier: Environment :: Web Environment
Classifier: Framework :: Django
Classifier: Intended Audience :: Developers
Classifier: License :: OSI Approved :: BSD License
Classifier: Operating System :: OS Independent
Classifier: Programming Language :: Python
Classifier: Topic :: Software Development :: Libraries :: Python Modules
